COPYING
LICENSE
MANIFEST.in
ez_setup.py
setup.cfg
setup.py
jump/__init__.py
jump.egg-info/PKG-INFO
jump.egg-info/SOURCES.txt
jump.egg-info/dependency_links.txt
jump.egg-info/entry_points.txt
jump.egg-info/not-zip-safe
jump.egg-info/requires.txt
jump.egg-info/top_level.txt
jump/ant/__init__.py
jump/ant/jython_compiler.py
jump/commands/__init__.py
jump/commands/ant.py
jump/commands/app.py
jump/commands/exe.py
jump/commands/jar.py
jump/commands/jarlib.py
jump/commands/main.py
jump/commands/war.py
jump/lib/.DS_Store
jump/lib/JavaApplicationStub
jump/lib/jarbundler-2.1.0.jar
jump/lib/jump-ant-tasks.jar
jump/lib/jump-jython-factory.jar
jump/lib/one-jar-ant-task-0.96.jar
jump/lib/ant-contrib/LICENSE.txt
jump/lib/ant-contrib/ant-contrib.jar
jump/lib/fmpp-0.9.14/LICENSE.txt
jump/lib/fmpp-0.9.14/LICENSE_ANT.txt
jump/lib/fmpp-0.9.14/LICENSE_FREEMARKER.txt
jump/lib/fmpp-0.9.14/LICENSE_ORO.txt
jump/lib/fmpp-0.9.14/LICENSE_RESOLVER.txt
jump/lib/fmpp-0.9.14/bsh.jar
jump/lib/fmpp-0.9.14/fmpp.jar
jump/lib/fmpp-0.9.14/freemarker.jar
jump/lib/fmpp-0.9.14/oro.jar
jump/lib/launch4j/.DS_Store
jump/lib/launch4j/LICENSE.txt
jump/lib/launch4j/launch4j.jar
jump/lib/launch4j/xstream.jar
jump/lib/launch4j/bin/COPYING
jump/lib/launch4j/bin/ld
jump/lib/launch4j/bin/readme.txt
jump/lib/launch4j/bin/windres
jump/lib/launch4j/head/LICENSE.txt
jump/lib/launch4j/head/consolehead.o
jump/lib/launch4j/head/guihead.o
jump/lib/launch4j/head/head.o
jump/lib/launch4j/w32api/MinGW.LICENSE.txt
jump/lib/launch4j/w32api/crt2.o
jump/lib/launch4j/w32api/libadvapi32.a
jump/lib/launch4j/w32api/libgcc.a
jump/lib/launch4j/w32api/libkernel32.a
jump/lib/launch4j/w32api/libmingw32.a
jump/lib/launch4j/w32api/libmsvcrt.a
jump/lib/launch4j/w32api/libshell32.a
jump/lib/launch4j/w32api/libuser32.a
jump/resources/LICENSE.One-JAR
jump/resources/jump.icns
jump/resources/jump.ico
jump/templates/Main.java
jump/templates/appengine-web.xml
jump/templates/build.xml
jump/templates/web.xml