Metadata-Version: 1.0
Name: jump
Version: 0.9.7.4
Summary: Jump is a build tool for distributing Java and Jython applications in a really simple step.
Home-page: http://opensource.ollix.com/jump
Author: Olli Wang
Author-email: olliwang@ollix.com
License: GPLv3
Platform: UNKNOWN
Classifier: Intended Audience :: Developers
Classifier: License :: OSI Approved
Classifier: Operating System :: OS Independent
Classifier: Programming Language :: Python
Classifier: Topic :: Software Development :: Build Tools
